gitlabenv2csv/__init__.py
gitlabenv2csv/__main__.py
gitlabenv2csv-1.0.2.dist-info/LICENSE
gitlabenv2csv-1.0.2.dist-info/METADATA
gitlabenv2csv-1.0.2.dist-info/WHEEL
gitlabenv2csv-1.0.2.dist-info/entry_points.txt
gitlabenv2csv-1.0.2.dist-info/top_level.txt
gitlabenv2csv-1.0.2.dist-info/RECORD
