Metadata-Version: 2.1
Name: gitlabenv2csv
Version: 1.0.2
Summary: gitlabenv2csv allows you to download GitLab ENV variables to a csv file.
Home-page: https://github.com/zales/gitlabenv2csv
Author: Ondrej Zalesky
Author-email: o.zalesky@gmail.com
License: MIT
Platform: UNKNOWN
Classifier: License :: OSI Approved :: MIT License
Classifier: Programming Language :: Python
Classifier: Programming Language :: Python :: 3
Requires-Dist: ConfigArgParse
Requires-Dist: python-dateutil
Requires-Dist: python-gitlab
Requires-Dist: pandas-schema
